README.rst
setup.py
pyplan/__init__.py
pyplan/core.py
pyplan/helpers.py
pyplan/plots.py
pyplan.egg-info/PKG-INFO
pyplan.egg-info/SOURCES.txt
pyplan.egg-info/dependency_links.txt
pyplan.egg-info/requires.txt
pyplan.egg-info/top_level.txt