Metadata-Version: 1.1
Name: pyplan
Version: 0.0.1
Summary: Tools for alternatives analysis of progressive capital planning projects
Home-page: https://github.com/aerispaha/pyplan
Author: Adam Erispaha
Author-email: aerispaha@gmail.com
License: MIT License
Platform: OS Independent
Classifier: Development Status :: 3 - Alpha
Classifier: License :: OSI Approved :: MIT License
Classifier: Operating System :: OS Independent
Classifier: Programming Language :: Python :: 2.7
